CHANGELOG.md
improved_backoff/__init__.py
improved_backoff/_async.py
improved_backoff/_common.py
improved_backoff/_decorator.py
improved_backoff/_jitter.py
improved_backoff/_sync.py
improved_backoff/_typing.py
improved_backoff/_wait_gen.py
improved_backoff/py.typed
improved_backoff/types.py
LICENSE
README.md
improved_backoff-1.2.dist-info/LICENSE
improved_backoff-1.2.dist-info/LICENSE.backoff
improved_backoff-1.2.dist-info/WHEEL
improved_backoff-1.2.dist-info/METADATA
improved_backoff-1.2.dist-info/RECORD
